zen_orchestrator.py
agent_interface/__init__.py
agent_interface/base_agent.py
netra_zen-1.3.12.dist-info/licenses/LICENSE.md
scripts/__init__.py
scripts/__main__.py
scripts/agent_cli.py
scripts/agent_logs.py
scripts/bump_version.py
scripts/chunk_creator.py
scripts/chunking_analyzer.py
scripts/demo_log_collection.py
scripts/embed_release_credentials.py
scripts/test_apex_telemetry_debug.py
scripts/verify_log_transmission.py
shared/README.md
shared/TIMING_FIX_COMPLETE.md
shared/__init__.py
shared/windows_encoding.py
shared/types/__init__.py
shared/types/websocket_closure_codes.py
token_budget/__init__.py
token_budget/budget_manager.py
token_budget/models.py
token_budget/visualization.py
token_transparency/__init__.py
token_transparency/claude_pricing_engine.py
zen/__init__.py
zen/__main__.py
zen/telemetry/__init__.py
zen/telemetry/apex_telemetry.py
zen/telemetry/embedded_credentials.py
zen/telemetry/manager.py
netra_zen-1.3.12.dist-info/METADATA
netra_zen-1.3.12.dist-info/WHEEL
netra_zen-1.3.12.dist-info/entry_points.txt
netra_zen-1.3.12.dist-info/top_level.txt
netra_zen-1.3.12.dist-info/RECORD
