Metadata-Version: 2.4
Name: netra-zen
Version: 1.3.12
Summary: Multi-instance Claude orchestrator for parallel task execution
Home-page: https://github.com/netra-systems/zen
Author:  Systems
Author-email: Netra Systems <pypi@netrasystems.ai>
License: MIT
Project-URL: Homepage, https://github.com/netra-systems/zen
Project-URL: Documentation, https://github.com/netra-systems/zen#readme
Project-URL: Repository, https://github.com/netra-systems/zen.git
Project-URL: Bug Tracker, https://github.com/netra-systems/zen/issues
Project-URL: Changelog, https://github.com/netra-systems/zen/blob/main/CHANGELOG.md
Keywords: claude,ai,orchestration,parallel,automation,llm,anthropic
Classifier: Development Status :: 4 - Beta
Classifier: Intended Audience :: Developers
Classifier: License :: Other/Proprietary License
Classifier: Operating System :: OS Independent
Classifier: Programming Language :: Python :: 3
Classifier: Programming Language :: Python :: 3.8
Classifier: Programming Language :: Python :: 3.9
Classifier: Programming Language :: Python :: 3.10
Classifier: Programming Language :: Python :: 3.11
Classifier: Programming Language :: Python :: 3.12
Classifier: Topic :: Software Development :: Libraries :: Python Modules
Classifier: Topic :: Software Development :: Quality Assurance
Classifier: Topic :: System :: Distributed Computing
Requires-Python: >=3.8
License-File: LICENSE.md
Requires-Dist: PyYAML>=6.0
Requires-Dist: python-dateutil>=2.8.2
Requires-Dist: aiohttp>=3.8.0
Requires-Dist: websockets>=11.0
Requires-Dist: rich>=13.0.0
Requires-Dist: PyJWT>=2.8.0
Requires-Dist: psutil>=5.9.0
Requires-Dist: opentelemetry-sdk>=1.20.0
Requires-Dist: opentelemetry-exporter-gcp-trace>=1.6.0
Requires-Dist: google-cloud-trace>=1.11.0
Provides-Extra: dev
Requires-Dist: pytest>=7.0.0; extra == "dev"
Requires-Dist: pytest-asyncio>=0.21.0; extra == "dev"
Requires-Dist: pytest-cov>=4.0.0; extra == "dev"
Requires-Dist: black>=23.0.0; extra == "dev"
Requires-Dist: ruff>=0.1.0; extra == "dev"
Requires-Dist: mypy>=1.0.0; extra == "dev"
Provides-Extra: netra
Requires-Dist: netraoptimizer>=1.0.0; extra == "netra"
Dynamic: author
Dynamic: home-page
Dynamic: license-file
Dynamic: requires-python
